CrumblPy/__init__.py
CrumblPy/aws.py
CrumblPy/email.py
CrumblPy/slack.py
CrumblPy/snowflake.py
crumblpy-1.1.9.dist-info/licenses/LICENSE
tests/__init__.py
tests/test_aws.py
tests/test_email.py
tests/test_slack.py
tests/test_snowflake.py
crumblpy-1.1.9.dist-info/METADATA
crumblpy-1.1.9.dist-info/WHEEL
crumblpy-1.1.9.dist-info/top_level.txt
crumblpy-1.1.9.dist-info/RECORD
