Metadata-Version: 2.4
Name: CrumblPy
Version: 1.1.9
Summary: Common utility functions for Crumbl Data Team
Author: Crumbl Data Team
Author-email: steven.wang@crumbl.com
License: Proprietary
Requires-Python: >=3.9
License-File: LICENSE
Requires-Dist: boto3>=1.40.19
Requires-Dist: cryptography>=43.0.1
Requires-Dist: google_api_python_client>=2.125.0
Requires-Dist: google-auth-oauthlib>=1.2.0
Requires-Dist: numpy>=1.26.0
Requires-Dist: pandas>=2.2.3
Requires-Dist: prefect>=3.0.3
Requires-Dist: protobuf>=4.25.5
Requires-Dist: pyarrow>=17.0.0
Requires-Dist: slack_sdk>=3.21.3
Requires-Dist: snowflake-connector-python>=3.17.0
Provides-Extra: dev
Requires-Dist: pytest>=7.0.0; extra == "dev"
Requires-Dist: pytest-mock>=3.10.0; extra == "dev"
Dynamic: author
Dynamic: author-email
Dynamic: description
Dynamic: description-content-type
Dynamic: license
Dynamic: license-file
Dynamic: provides-extra
Dynamic: requires-dist
Dynamic: requires-python
Dynamic: summary
